skill_easter_eggs/LICENSE
skill_easter_eggs/README.md
skill_easter_eggs/__init__.py
skill_easter_eggs/constants.py
skill_easter_eggs/skill.json
skill_easter_eggs/stardate.py
skill_easter_eggs/version.py
skill_easter_eggs/locale/de-de/dialog/bad_file.dialog
skill_easter_eggs/locale/de-de/dialog/languages.dialog
skill_easter_eggs/locale/de-de/dialog/pod.dialog
skill_easter_eggs/locale/de-de/dialog/rock_paper_scissors_lizard_spock.dialog
skill_easter_eggs/locale/de-de/dialog/rule1.dialog
skill_easter_eggs/locale/de-de/dialog/rule2.dialog
skill_easter_eggs/locale/de-de/dialog/rule3.dialog
skill_easter_eggs/locale/de-de/dialog/stardate.dialog
skill_easter_eggs/locale/de-de/regex/Law.rx
skill_easter_eggs/locale/de-de/vocab/adult_mode_keyword.voc
skill_easter_eggs/locale/de-de/vocab/arnold_keyword.voc
skill_easter_eggs/locale/de-de/vocab/bender_keyword.voc
skill_easter_eggs/locale/de-de/vocab/duke_nukem_keyword.voc
skill_easter_eggs/locale/de-de/vocab/glados_keyword.voc
skill_easter_eggs/locale/de-de/vocab/grandma_mode_keyword.voc
skill_easter_eggs/locale/de-de/vocab/hal_keyword.voc
skill_easter_eggs/locale/de-de/vocab/languages_you_speak_keyword.voc
skill_easter_eggs/locale/de-de/vocab/law_keyword.voc
skill_easter_eggs/locale/de-de/vocab/pod_bay_doors_keyword.voc
skill_easter_eggs/locale/de-de/vocab/portal_keyword.voc
skill_easter_eggs/locale/de-de/vocab/robotics_keyword.voc
skill_easter_eggs/locale/de-de/vocab/rock_paper_scissors_lizard_spock_keyword.voc
skill_easter_eggs/locale/de-de/vocab/stardate_keyword.voc
skill_easter_eggs/locale/en-us/dialog/bad_file.dialog
skill_easter_eggs/locale/en-us/dialog/invalid_law.dialog
skill_easter_eggs/locale/en-us/dialog/languages.dialog
skill_easter_eggs/locale/en-us/dialog/pod.dialog
skill_easter_eggs/locale/en-us/dialog/rock_paper_scissors_lizard_spock.dialog
skill_easter_eggs/locale/en-us/dialog/rule0.dialog
skill_easter_eggs/locale/en-us/dialog/rule1.dialog
skill_easter_eggs/locale/en-us/dialog/rule2.dialog
skill_easter_eggs/skill_easter_eggs.egg-info/PKG-INFO
skill_easter_eggs/skill_easter_eggs.egg-info/SOURCES.txt
skill_easter_eggs/skill_easter_eggs.egg-info/dependency_links.txt
skill_easter_eggs/skill_easter_eggs.egg-info/entry_points.txt
skill_easter_eggs/skill_easter_eggs.egg-info/requires.txt
skill_easter_eggs/skill_easter_eggs.egg-info/top_level.txt
skill_easter_eggs-1.0.0.dist-info/LICENSE
skill_easter_eggs-1.0.0.dist-info/METADATA
skill_easter_eggs-1.0.0.dist-info/WHEEL
skill_easter_eggs-1.0.0.dist-info/entry_points.txt
skill_easter_eggs-1.0.0.dist-info/top_level.txt
skill_easter_eggs-1.0.0.dist-info/RECORD
