Metadata-Version: 2.1
Name: skill-easter-eggs
Version: 1.0.0
Home-page: https://github.com/OpenVoiceOS/skill-easter-eggs
Author: Jarbas
Author-email: jarbas@openvoiceos.com
License: BSD-3-Clause
License-File: LICENSE
Requires-Dist: ovos-lingua-franca ~=0.4.8a1
Requires-Dist: python-dateutil ~=2.9.0
Requires-Dist: ovos-utils >=0.0.38,~=0.0
Requires-Dist: ovos-workshop >=0.0.15,~=0.0
Requires-Dist: ovos-bus-client >=0.0.6,~=0.0
Requires-Dist: ovos-lingua-franca >=0.4.7,~=0.0
Requires-Dist: ovos-mark1-utils ~=0.0.0a2
Provides-Extra: test
Requires-Dist: neon-minerva >=0.2.0 ; extra == 'test'
Requires-Dist: ovos-plugin-manager ; extra == 'test'
Requires-Dist: pytest ; extra == 'test'
Requires-Dist: pytest-cov ; extra == 'test'
Requires-Dist: ovos-config ; extra == 'test'
